{"cameraMode":{"drawMode":0,"name":"Shaded","section":"Shading Mode"},"sceneLighting":true,"audioPlay":false,"sceneViewState":{"m_AlwaysRefresh":false,"showFog":true,"showSkybox":true,"showFlares":true,"showImageEffects":true,"showParticleSystems":true,"showVisualEffectGraphs":true,"m_FxEnabled":true},"in2DMode":false,"pivot":{"x":9.81813907623291,"y":-108.3575668334961,"z":45.13676452636719},"rotation":{"x":0.3201978802680969,"y":0.07520006597042084,"z":-0.025547532364726068,"w":0.9440550208091736},"size":62.744346618652347,"orthographic":false}