{"cameraMode":{"drawMode":0,"name":"Shaded","section":"Shading Mode"},"sceneLighting":true,"audioPlay":false,"sceneViewState":{"m_AlwaysRefresh":false,"showFog":true,"showSkybox":true,"showFlares":true,"showImageEffects":true,"showParticleSystems":true,"showVisualEffectGraphs":true,"m_FxEnabled":true},"in2DMode":false,"pivot":{"x":128.35922241210938,"y":-80.05655670166016,"z":-23.60791778564453},"rotation":{"x":-0.06153985485434532,"y":0.8436383605003357,"z":-0.5241206884384155,"w":-0.09921502321958542},"size":24.281431198120118,"orthographic":false}